pyateos/__init__.py
pyateos/modules/__init__.py
pyateos/modules/eos_pyateos.py
pyateos_ansible-1.0.7.dist-info/LICENSE
pyateos_ansible-1.0.7.dist-info/METADATA
pyateos_ansible-1.0.7.dist-info/WHEEL
pyateos_ansible-1.0.7.dist-info/top_level.txt
pyateos_ansible-1.0.7.dist-info/RECORD
