Metadata-Version: 2.1
Name: pyateos-ansible
Version: 1.0.7
Summary: Ansible module pyATEOS framework.
Home-page: https://github.com/lvrfrc87/pyateos-ansible
Author: Federico Olivieri
Author-email: lvrfrc87@gmail.com
License: UNKNOWN
Platform: UNKNOWN
Classifier: Topic :: Utilities
Classifier: Programming Language :: Python
Classifier: Programming Language :: Python :: 3
Classifier: Programming Language :: Python :: 3.5
Classifier: Programming Language :: Python :: 3.6
Classifier: Programming Language :: Python :: 3.7
Classifier: Operating System :: POSIX :: Linux
Classifier: Operating System :: MacOS
Requires-Dist: ansible
Requires-Dist: jsondiff
Requires-Dist: jmespath
